examples/28_pinned_comment_detection.py
examples/save_live_responses.py
examples/features/01_get_video_metadata.py
examples/features/02_get_channel_metadata.py
examples/features/03_get_channel_videos_basic.py
examples/features/04_get_channel_videos_full_metadata.py
examples/features/05_filter_channel_videos_by_date.py
examples/features/06_get_playlist_videos.py
examples/features/07_filter_playlist_by_date.py
examples/features/08_filter_by_view_count.py
examples/features/09_filter_by_duration.py
examples/features/10_filter_by_like_count.py
examples/features/11_filter_by_description_snippet.py
examples/features/12_filter_by_title.py
examples/features/13_filter_by_category.py
examples/features/14_filter_by_keywords.py
examples/features/15_filter_by_full_description.py
examples/features/16_filter_by_publish_date.py
examples/features/18_benchmark_caching.py
examples/features/19_alternative_caching_sqlite.py
examples/features/20_get_channel_shorts_basic.py
examples/features/21_get_channel_shorts_full_metadata.py
examples/features/22_get_video_comments.py
examples/features/23_filter_validation.py
examples/features/24_multi_component_filter.py
examples/features/25_comment_sorting_demonstration.py
examples/features/26_hierarchical_comments_demonstration.py
examples/features/27a_comment_deduplication_sorting.py
examples/features/27b_comment_analysis_hierarchical.py
examples/features/29_progress_callback_demonstration.py
examples/features/30_structured_reply_fetching.py
examples/features/31_get_comments_since_date.py
examples/features/32_get_video_transcript.py
tests/__init__.py
tests/conftest.py
tests/test_caching.py
tests/test_channel_fetcher.py
tests/test_client.py
tests/test_comment_fetcher.py
tests/test_date_utils.py
tests/test_filtering.py
tests/test_parsing.py
tests/test_playlist.py
tests/test_playlist_fetcher.py
tests/test_transcript_fetcher.py
tests/test_validation.py
tests/test_video_fetcher.py
yt_meta/__init__.py
yt_meta/caching.py
yt_meta/client.py
yt_meta-0.4.0.dist-info/licenses/LICENSE
yt_meta-0.4.0.dist-info/METADATA
yt_meta-0.4.0.dist-info/WHEEL
yt_meta-0.4.0.dist-info/top_level.txt
yt_meta-0.4.0.dist-info/RECORD
