Metadata-Version: 2.4
Name: yt-meta
Version: 0.4.0
Summary: A lightweight, dependency-free library for fetching YouTube metadata.
Author-email: Shane <shane.isley@gmail.com>
License: MIT License
Project-URL: Homepage, https://github.com/shaneisley/yt-meta
Classifier: License :: OSI Approved :: MIT License
Classifier: Programming Language :: Python
Classifier: Programming Language :: Python :: 3
Requires-Python: >=3.10
License-File: LICENSE
Requires-Dist: httpx
Requires-Dist: beautifulsoup4
Requires-Dist: dateparser
Requires-Dist: pytz
Requires-Dist: loguru
Requires-Dist: diskcache>=5.6.3
Requires-Dist: pytest-mock>=3.14.1
Requires-Dist: rich>=14.0.0
Requires-Dist: sqlitedict>=2.1.0
Requires-Dist: youtube-transcript-api>=1.1.0
Provides-Extra: dev
Requires-Dist: pytest; extra == "dev"
Requires-Dist: pytest-cov; extra == "dev"
Requires-Dist: pytest-mock; extra == "dev"
Requires-Dist: ruff; extra == "dev"
Requires-Dist: tqdm; extra == "dev"
Dynamic: license-file
